Workbook

Sheet Guía
A1: Modelo preliminar — Carga rápida pública en Panamá
A3: Propósito | B3: Modelo de sensibilidad para evaluar un sitio DC; no es una cotización ni una proyección de inversión.
A4: Cómo usar | B4: Edite las celdas verdes de Supuestos. Las hojas de escenarios actualizan las fórmulas al abrir el archivo en Excel.
A5: Advertencia | B5: Reemplazar referencias históricas de enero–agosto de 2026 con el pliego vigente y el estudio de conexión de la ubicación.
A6: Fuentes | B6: ASEP tarifas y CVC 2026; propuesta de pliego 2026–2030; precio público observado B/.0,35–0,50/kWh como referencia sectorial.

Sheet Supuestos
A1: Supuestos editables
A3: Concepto | B3: Valor | C3: Unidad | D3: Uso en el modelo | E3: Fuente / nota
A4: Potencia nominal | B4: 120 | C4: kW | D4: Capacidad de cargador DC | E4: Supuesto; validar con diseño
A5: Días por mes | B5: 30 | C5: días | D5: Conversión de utilización a kWh mensuales | E5: Supuesto de modelación
A6: Eficiencia de entrega | B6: 0.92 | C6: % | D6: kWh comprados = kWh entregados / eficiencia | E6: Reemplazar por ficha técnica
A7: Demanda facturada | B7: 120 | C7: kW | D7: Cargo de demanda mensual | E7: Validar con simultaneidad / load management
A8: EDEMET energía MTD | B8: 0.16001 | C8: B/./kWh | D8: Componente energía | E8: ASEP ene–ago 2026
A9: EDEMET CVC | B9: -0.00915 | C9: B/./kWh | D9: Variación combustible | E9: ASEP agosto 2026; variable
A10: EDEMET demanda MTD | B10: 20.62 | C10: B/./kW-mes | D10: Cargo de demanda | E10: ASEP ene–ago 2026
A11: EDEMET cargo fijo | B11: 14.27 | C11: B/./mes | D11: Cargo fijo | E11: ASEP ene–ago 2026
A12: Precio público bajo | B12: 0.35 | C12: B/./kWh | D12: Escenario conservador | E12: Banda observada a validar
A13: Precio público base | B13: 0.425 | C13: B/./kWh | D13: Escenario base | E13: Punto medio de banda observada
A14: Precio público alto | B14: 0.5 | C14: B/./kWh | D14: Escenario alto uso | E14: Banda observada a validar
A15: Utilización conservadora | B15: 0.05 | C15: % | D15: Horas equivalentes | E15: Escenario de sensibilidad
... A17: Utilización alta | B17: 0.3 | C17: % | D17: Horas equivalentes | E17: Escenario de sensibilidad

Sheet Escenarios EDEMET
A1: Escenarios — Estación DC 120 kW · EDEMET
A3: Escenario | B3: Utilización | C3: Precio de venta | D3: kWh entregados/mes | E3: kWh comprados/mes | F3: Ingreso/mes | G3: Energía + CVC | H3: Demanda + fijo | I3: Costo total de red | J3: Costo efectivo/kWh | K3: Contribución tras red
A4: Conservador | B4: =Supuestos!B15 | C4: =Supuestos!B12 | D4: =Supuestos!B4*24*Supuestos!B5*B4 | E4: =D4/Supuestos!B6 | F4: =D4*C4 | G4: =E4*(Supuestos!B8+Supuestos!B9) | H4: =Supuestos!B7*Supuestos!B10+Supuestos!B11 | I4: =G4+H4 | J4: =I4/D4 | K4: =F4-I4
A5: Base | B5: =Supuestos!B16 | C5: =Supuestos!B13 | D5: =Supuestos!B4*24*Supuestos!B5*B5 | E5: =D5/Supuestos!B6 | F5: =D5*C5 | G5: =E5*(Supuestos!B8+Supuestos!B9) | H5: =Supuestos!B7*Supuestos!B10+Supuestos!B11 | I5: =G5+H5 | J5: =I5/D5 | K5: =F5-I5
A6: Alto uso | B6: =Supuestos!B17 | C6: =Supuestos!B14 | D6: =Supuestos!B4*24*Supuestos!B5*B6 | E6: =D6/Supuestos!B6 | F6: =D6*C6 | G6: =E6*(Supuestos!B8+Supuestos!B9) | H6: =Supuestos!B7*Supuestos!B10+Supuestos!B11 | I6: =G6+H6 | J6: =I6/D6 | K6: =F6-I6

Sheet Sensibilidad zonas
A1: Sensibilidad territorial — caso base de 15%
A3: Zona | B3: Energía | C3: CVC | D3: Demanda | E3: Fijo | F3: Costo efectivo/kWh | G3: Ingreso/mes | H3: Costo red/mes | I3: Contribución tras red
A4: EDEMET | B4: 0.16001 | C4: -0.00915 | D4: 20.62 | E4: 14.27 | F4: =(((Supuestos!B4*24*Supuestos!B5*Supuestos!B16)/Supuestos!B6)*(B4+C4)+(Supuestos!B7*D4)+E4)/(Supuestos!B4*24*Supuestos!B5*Supuestos!B16) | G4: =Supuestos!B4*24*Supuestos!B5*Supuestos!B16*Supuestos!B13 | H4: =G4-(G4-((Supuestos!B4*24*Supuestos!B5*Supuestos!B16)/Supuestos!B6)*(B4+C4)-(Supuestos!B7*D4)-E4) | I4: =G4-H4
A5: ENSA | B5: 0.15396 | C5: 0.00052 | D5: 12.45 | E5: 9.06 | F5: =(((Supuestos!B4*24*Supuestos!B5*Supuestos!B16)/Supuestos!B6)*(B5+C5)+(Supuestos!B7*D5)+E5)/(Supuestos!B4*24*Supuestos!B5*Supuestos!B16) | G5: =Supuestos!B4*24*Supuestos!B5*Supuestos!B16*Supuestos!B13 | H5: =G5-(G5-((Supuestos!B4*24*Supuestos!B5*Supuestos!B16)/Supuestos!B6)*(B5+C5)-(Supuestos!B7*D5)-E5) | I5: =G5-H5
A6: EDECHI | B6: 0.13479 | C6: -0.0151 | D6: 24.53 | E6: 14.21 | F6: =(((Supuestos!B4*24*Supuestos!B5*Supuestos!B16)/Supuestos!B6)*(B6+C6)+(Supuestos!B7*D6)+E6)/(Supuestos!B4*24*Supuestos!B5*Supuestos!B16) | G6: =Supuestos!B4*24*Supuestos!B5*Supuestos!B16*Supuestos!B13 | H6: =G6-(G6-((Supuestos!B4*24*Supuestos!B5*Supuestos!B16)/Supuestos!B6)*(B6+C6)-(Supuestos!B7*D6)-E6) | I6: =G6-H6
